im/__init__.py
image_utils/__init__.py
image_utils/custom_library_ops.py
image_utils/file_utils.py
image_utils/im.py
image_utils/library_ops.py
image_utils/process_utils.py
image_utils/standalone_image_utils.py
image_utils/torch_utils.py
image_utils/video_utils.py
image_utilities-0.0.3.dist-info/METADATA
image_utilities-0.0.3.dist-info/WHEEL
image_utilities-0.0.3.dist-info/RECORD
