Metadata-Version: 2.4
Name: image_utilities
Version: 0.0.3
Summary: A utility library for common image and video operations.
Project-URL: Homepage, https://github.com/alexanderswerdlow/image_utils
Author-email: Alexander Swerdlow <aswerdlow1@gmail.com>
Classifier: License :: OSI Approved :: MIT License
Classifier: Operating System :: OS Independent
Classifier: Programming Language :: Python :: 3
Requires-Python: >=3.8
Requires-Dist: einops>=0.3.0
Requires-Dist: jaxtyping>=0.2.19
Requires-Dist: numpy>=1.17
Requires-Dist: pillow>=8.0.0
Provides-Extra: cpu
Requires-Dist: lovely-tensors; extra == 'cpu'
Requires-Dist: torch; extra == 'cpu'
Requires-Dist: torchvision; extra == 'cpu'
Provides-Extra: cu118
Requires-Dist: lovely-tensors; extra == 'cu118'
Requires-Dist: torch; extra == 'cu118'
Requires-Dist: torchvision; extra == 'cu118'
Provides-Extra: cu124
Requires-Dist: lovely-tensors; extra == 'cu124'
Requires-Dist: torch; extra == 'cu124'
Requires-Dist: torchvision; extra == 'cu124'
Provides-Extra: dev
Requires-Dist: black; extra == 'dev'
Requires-Dist: joblib>=1.2.0; extra == 'dev'
Requires-Dist: lovely-numpy>=0.2.8; extra == 'dev'
Requires-Dist: opencv-python; extra == 'dev'
Requires-Dist: pytest; extra == 'dev'
Requires-Dist: pytest-cov; extra == 'dev'
Provides-Extra: video
Requires-Dist: av>=10.0.0; extra == 'video'
Requires-Dist: imageio[ffmpeg]>=2.23.0; extra == 'video'
